setup.py
duct/__init__.py
duct/aggregators.py
duct/interfaces.py
duct/objects.py
duct/service.py
duct/utils.py
duct/ihateprotobuf/__init__.py
duct/ihateprotobuf/proto_pb2.py
duct/logs/__init__.py
duct/logs/follower.py
duct/logs/parsers.py
duct/outputs/__init__.py
duct/outputs/bosun.py
duct/outputs/elasticsearch.py
duct/outputs/riemann.py
duct/protocol/__init__.py
duct/protocol/elasticsearch.py
duct/protocol/icmp.py
duct/protocol/riemann.py
duct/protocol/ssh.py
duct/protocol/sflow/__init__.py
duct/protocol/sflow/server.py
duct/protocol/sflow/protocol/__init__.py
duct/protocol/sflow/protocol/counters.py
duct/protocol/sflow/protocol/flows.py
duct/protocol/sflow/protocol/protocol.py
duct/protocol/sflow/protocol/utils.py
duct/sources/__init__.py
duct/sources/docker.py
duct/sources/generator.py
duct/sources/haproxy.py
duct/sources/munin.py
duct/sources/network.py
duct/sources/nginx.py
duct/sources/rabbitmq.py
duct/sources/redis.py
duct/sources/riak.py
duct/sources/riemann.py
duct/sources/sflow.py
duct/sources/snmp.py
duct/sources/unbound.py
duct/sources/database/__init__.py
duct/sources/database/elasticsearch.py
duct/sources/database/memcache.py
duct/sources/database/postgresql.py
duct/sources/linux/__init__.py
duct/sources/linux/basic.py
duct/sources/linux/ipsec.py
duct/sources/linux/process.py
duct/sources/linux/sensors.py
duct/sources/media/__init__.py
duct/sources/media/libav.py
duct/sources/python/__init__.py
duct/sources/python/uwsgi.py
duct/tests/__init__.py
duct/tests/test_duct.py
duct/tests/test_logs.py
duct/tests/test_service.py
duct/tests/test_sflow.py
duct/tests/test_sources.py
duct/tests/test_ssh.py
duct/tests/test_utils.py
ducted.egg-info/PKG-INFO
ducted.egg-info/SOURCES.txt
ducted.egg-info/dependency_links.txt
ducted.egg-info/requires.txt
ducted.egg-info/top_level.txt
twisted/plugins/duct_plugin.py