Metadata-Version: 1.1
Name: ducted
Version: 1.0
Summary: A monitoring agent and event processor
Home-page: http://github.com/ducted/duct
Author: Colin Alston
Author-email: colin.alston@gmail.com
License: MIT
Platform: UNKNOWN
Classifier: Development Status :: 5 - Production/Stable
Classifier: Intended Audience :: System Administrators
Classifier: License :: OSI Approved :: MIT License
Classifier: Operating System :: POSIX
Classifier: Programming Language :: Python
Classifier: Programming Language :: Python :: 2
Classifier: Programming Language :: Python :: 3
Classifier: Topic :: System :: Monitoring
